epic_free_games/__init__.py
epic_free_games/epic_games.py
epic_free_games-0.1.3.dist-info/METADATA
epic_free_games-0.1.3.dist-info/WHEEL
epic_free_games-0.1.3.dist-info/RECORD
