Metadata-Version: 2.1
Name: epic-free-games
Version: 0.1.3
Summary: A wrapper for Epic Games Store free games
Author: Hudson Brendon
Author-email: contato.hudsonbrendon@gmail.com
Requires-Python: >=3.10,<4.0
Classifier: Programming Language :: Python :: 3
Classifier: Programming Language :: Python :: 3.10
Classifier: Programming Language :: Python :: 3.11
Requires-Dist: requests (>=2.30.0,<3.0.0)
